alloy/__init__.py
alloy/__init__.pyi
alloy/ask.py
alloy/command.py
alloy/config.py
alloy/errors.py
alloy/py.typed
alloy/react.py
alloy/tool.py
alloy/types.py
alloy/models/__init__.py
alloy/models/anthropic.py
alloy/models/base.py
alloy/models/gemini.py
alloy/models/ollama.py
alloy/models/openai.py
alloy_ai-0.3.1.dist-info/licenses/LICENSE
alloy_ai-0.3.1.dist-info/METADATA
alloy_ai-0.3.1.dist-info/WHEEL
alloy_ai-0.3.1.dist-info/top_level.txt
alloy_ai-0.3.1.dist-info/RECORD
