Metadata-Version: 2.4
Name: alloy-ai
Version: 0.3.1
Summary: Alloy (Python): Python for logic. English for intelligence.
Author: George Lydakis
License: MIT
Project-URL: Homepage, https://github.com/lydakis/alloy
Project-URL: Repository, https://github.com/lydakis/alloy
Project-URL: Issues, https://github.com/lydakis/alloy/issues
Classifier: Intended Audience :: Developers
Classifier: Operating System :: OS Independent
Classifier: License :: OSI Approved :: MIT License
Classifier: Programming Language :: Python
Classifier: Programming Language :: Python :: 3
Classifier: Programming Language :: Python :: 3.10
Classifier: Programming Language :: Python :: 3.11
Classifier: Programming Language :: Python :: 3.12
Classifier: Programming Language :: Python :: 3.13
Requires-Python: >=3.10
License-File: LICENSE
Requires-Dist: openai<2,>=1.99.6
Requires-Dist: python-dotenv<2,>=1.1.1
Provides-Extra: openai
Requires-Dist: openai<2,>=1.99.6; extra == "openai"
Requires-Dist: python-dotenv<2,>=1.1.1; extra == "openai"
Provides-Extra: anthropic
Requires-Dist: anthropic<0.65,>=0.62.0; extra == "anthropic"
Provides-Extra: gemini
Requires-Dist: google-genai<2,>=1.29.0; extra == "gemini"
Requires-Dist: aiohttp<4,>=3.9; extra == "gemini"
Provides-Extra: providers
Requires-Dist: openai<2,>=1.99.6; extra == "providers"
Requires-Dist: python-dotenv<2,>=1.1.1; extra == "providers"
Requires-Dist: anthropic<0.65,>=0.62.0; extra == "providers"
Requires-Dist: google-genai<2,>=1.29.0; extra == "providers"
Requires-Dist: aiohttp<4,>=3.9; extra == "providers"
Requires-Dist: ollama<0.6,>=0.5.3; extra == "providers"
Provides-Extra: ollama
Requires-Dist: ollama<0.6,>=0.5.3; extra == "ollama"
Provides-Extra: dev
Requires-Dist: pytest<9,>=8.4.1; extra == "dev"
Requires-Dist: pytest-asyncio<1.2,>=0.25.2; extra == "dev"
Requires-Dist: pytest-cov<7,>=5.0.0; extra == "dev"
Requires-Dist: pytest-xdist<4,>=3.6.1; extra == "dev"
Requires-Dist: ruff<0.13,>=0.12.8; extra == "dev"
Requires-Dist: black<26,>=25.1.0; extra == "dev"
Requires-Dist: mypy<2,>=1.17.1; extra == "dev"
Requires-Dist: pre-commit<5,>=4.3.0; extra == "dev"
Requires-Dist: hypothesis<7,>=6.115.0; extra == "dev"
Requires-Dist: python-dateutil<3,>=2.9.0.post0; extra == "dev"
Provides-Extra: docs
Requires-Dist: mkdocs<2,>=1.6; extra == "docs"
Requires-Dist: mkdocs-material<10,>=9.5; extra == "docs"
Requires-Dist: mkdocstrings<0.31,>=0.28; extra == "docs"
Requires-Dist: mkdocstrings-python<2,>=1.16; extra == "docs"
Requires-Dist: pymdown-extensions<11,>=10.11; extra == "docs"
Requires-Dist: mkdocs-llmstxt<1,>=0.3; extra == "docs"
Requires-Dist: mkdocs-gen-files<1,>=0.5; extra == "docs"
Dynamic: license-file
